<?xml version="1.0" encoding="utf-8"?>
<enums>
  <!-- Automatically generated from dlc_forge_island.map (21391.13.03.13.1711.main) -->
  <enum name="MPObjectType">
    <value opcode="0" name="unused_spartan" />
    <value opcode="1" name="unused_elite" />
    <value opcode="2" name="monitor" />
    <value opcode="3" name="flag" />
    <value opcode="4" name="bomb" />
    <value opcode="5" name="ball" />
    <value opcode="6" name="area" />
    <value opcode="7" name="stand" />
    <value opcode="8" name="destination" />
    <value opcode="9" name="frag_grenade" />
    <value opcode="10" name="plasma_grenade" />
    <value opcode="11" name="unused_spike_grenade" />
    <value opcode="12" name="unused_firebomb_grenade" />
    <value opcode="13" name="dmr" />
    <value opcode="14" name="assault_rifle" />
    <value opcode="15" name="plasma_pistol" />
    <value opcode="16" name="unused_spike_rifle" />
    <value opcode="17" name="unused_smg" />
    <value opcode="18" name="unused_needle_rifle" />
    <value opcode="19" name="unused_plasma_repeater" />
    <value opcode="20" name="energy_sword" />
    <value opcode="21" name="magnum" />
    <value opcode="22" name="needler" />
    <value opcode="23" name="unused_plasma_rifle" />
    <value opcode="24" name="rocket_launcher" />
    <value opcode="25" name="shotgun" />
    <value opcode="26" name="sniper_rifle" />
    <value opcode="27" name="unused_brute_shot" />
    <value opcode="28" name="beam_rifle" />
    <value opcode="29" name="spartan_laser" />
    <value opcode="30" name="gravity_hammer" />
    <value opcode="31" name="unused_mauler" />
    <value opcode="32" name="unused_flamethrower" />
    <value opcode="33" name="unused_missile_pod" />
    <value opcode="34" name="warthog" />
    <value opcode="35" name="ghost" />
    <value opcode="36" name="scorpion" />
    <value opcode="37" name="wraith" />
    <value opcode="38" name="unused_banshee" />
    <value opcode="39" name="mongoose" />
    <value opcode="40" name="unused_chopper" />
    <value opcode="41" name="unused_prowler" />
    <value opcode="42" name="unused_hornet" />
    <value opcode="43" name="unused_stingray" />
    <value opcode="44" name="unused_heavy_wraith" />
    <value opcode="45" name="unused_falcon" />
    <value opcode="46" name="unused_sabre" />
    <value opcode="47" name="unused_sprint_equipment" />
    <value opcode="48" name="jet_pack_equipment" />
    <value opcode="49" name="unused_armor_lock_equipment" />
    <value opcode="50" name="unused_power_fist_equipment" />
    <value opcode="51" name="active_camo_equipment" />
    <value opcode="52" name="unused_ammo_pack_equipment" />
    <value opcode="53" name="unused_sensor_pack_equipment" />
    <value opcode="54" name="unused_revenant" />
    <value opcode="55" name="unused_pickup" />
    <value opcode="56" name="unused_prototype_covey_sniper" />
    <value opcode="57" name="unused_territory_static" />
    <value opcode="58" name="ctf_flag_return_area" />
    <value opcode="59" name="ctf_flag_spawn_point" />
    <value opcode="60" name="respawn_zone" />
    <value opcode="61" name="unused_invasion_elite_buy" />
    <value opcode="62" name="unused_invasion_elite_drop" />
    <value opcode="63" name="unused_invasion_slayer" />
    <value opcode="64" name="unused_invasion_spartan_buy" />
    <value opcode="65" name="unused_invasion_spartan_drop" />
    <value opcode="66" name="unused_invasion_spawn_controller" />
    <value opcode="67" name="unused_oddball_ball_spawn_point" />
    <value opcode="68" name="unused_plasma_launcher" />
    <value opcode="69" name="unused_fusion_coil" />
    <value opcode="70" name="unused_unsc_shield_generator" />
    <value opcode="71" name="unused_cov_shield_generator" />
    <value opcode="72" name="initial_spawn_point" />
    <value opcode="73" name="unused_invasion_vehicle_req" />
    <value opcode="74" name="unused_vehicle_req_floor" />
    <value opcode="75" name="unused_wall_switch" />
    <value opcode="76" name="unused_health_station" />
    <value opcode="77" name="unused_req_unsc_laser" />
    <value opcode="78" name="unused_req_unsc_dmr" />
    <value opcode="79" name="unused_req_unsc_rocket" />
    <value opcode="80" name="unused_req_unsc_shotgun" />
    <value opcode="81" name="unused_req_unsc_sniper" />
    <value opcode="82" name="unused_req_covy_launcher" />
    <value opcode="83" name="unused_req_covy_needler" />
    <value opcode="84" name="unused_req_covy_sniper" />
    <value opcode="85" name="unused_req_covy_sword" />
    <value opcode="86" name="unused_shock_loadout" />
    <value opcode="87" name="unused_specialist_loadout" />
    <value opcode="88" name="unused_assassin_loadout" />
    <value opcode="89" name="unused_infiltrator_loadout" />
    <value opcode="90" name="unused_warrior_loadout" />
    <value opcode="91" name="unused_combatant_loadout" />
    <value opcode="92" name="unused_engineer_loadout" />
    <value opcode="93" name="unused_infantry_loadout" />
    <value opcode="94" name="unused_operator_loadout" />
    <value opcode="95" name="unused_recon_loadout" />
    <value opcode="96" name="unused_scout_loadout" />
    <value opcode="97" name="unused_seeker_loadout" />
    <value opcode="98" name="unused_airborne_loadout" />
    <value opcode="99" name="unused_ranger_loadout" />
    <value opcode="100" name="unused_req_buy_banshee" />
    <value opcode="101" name="unused_req_buy_falcon" />
    <value opcode="102" name="unused_req_buy_ghost" />
    <value opcode="103" name="unused_req_buy_mongoose" />
    <value opcode="104" name="unused_req_buy_revenant" />
    <value opcode="105" name="unused_req_buy_scorpion" />
    <value opcode="106" name="unused_req_buy_warthog" />
    <value opcode="107" name="unused_req_buy_wraith" />
    <value opcode="108" name="unused_fireteam_1_respawn_zone" />
    <value opcode="109" name="unused_fireteam_2_respawn_zone" />
    <value opcode="110" name="unused_fireteam_3_respawn_zone" />
    <value opcode="111" name="unused_fireteam_4_respawn_zone" />
    <value opcode="112" name="unused_semi" />
    <value opcode="113" name="unused_soccer_ball" />
    <value opcode="114" name="unused_golf_ball" />
    <value opcode="115" name="unused_golf_ball_blue" />
    <value opcode="116" name="unused_golf_ball_red" />
    <value opcode="117" name="unused_golf_club" />
    <value opcode="118" name="unused_golf_cup" />
    <value opcode="119" name="unused_golf_tee" />
    <value opcode="120" name="unused_dice" />
    <value opcode="121" name="unused_space_crate" />
    <value opcode="122" name="unused_eradicator_loadout" />
    <value opcode="123" name="unused_saboteur_loadout" />
    <value opcode="124" name="unused_grenadier_loadout" />
    <value opcode="125" name="unused_marksman_loadout" />
    <value opcode="126" name="unused_flare" />
    <value opcode="127" name="unused_glow_stick" />
    <value opcode="128" name="unused_elite_shot" />
    <value opcode="129" name="unused_grenade_launcher" />
    <value opcode="130" name="unused_phantom_approach" />
    <value opcode="131" name="hologram_equipment" />
    <value opcode="132" name="unused_evade_equipment" />
    <value opcode="133" name="unused_unsc_data_core" />
    <value opcode="134" name="unused_danger_zone" />
    <value opcode="135" name="unused_teleporter_sender" />
    <value opcode="136" name="unused_teleporter_reciever" />
    <value opcode="137" name="unused_teleporter_2way" />
    <value opcode="138" name="unused_data_core_beam" />
    <value opcode="139" name="unused_phantom_overwatch" />
    <value opcode="140" name="unused_longsword" />
    <value opcode="141" name="unused_invisible_cube_of_derek" />
    <value opcode="142" name="unused_phantom_scenery" />
    <value opcode="143" name="unused_pelican_scenery" />
    <value opcode="144" name="unused_phantom" />
    <value opcode="145" name="unused_pelican" />
    <value opcode="146" name="unused_armory_shelf" />
    <value opcode="147" name="unused_cov_resupply_capsule" />
    <value opcode="148" name="unused_covy_drop_pod" />
    <value opcode="149" name="unused_invisible_marker" />
    <value opcode="150" name="weak_respawn_zone" />
    <value opcode="151" name="weak_anti_respawn_zone" />
    <value opcode="152" name="unused_phantom_device" />
    <value opcode="153" name="unused_resupply_capsule" />
    <value opcode="154" name="unused_resupply_capsule_open" />
    <value opcode="155" name="unused_weapon_box" />
    <value opcode="156" name="unused_tech_console_stationary" />
    <value opcode="157" name="unused_tech_console_wall" />
    <value opcode="158" name="mp_cinematic_camera" />
    <value opcode="159" name="unused_invis_cov_resupply_capsule" />
    <value opcode="160" name="unused_cov_power_module" />
    <value opcode="161" name="unused_flak_cannon" />
    <value opcode="162" name="unused_dropzone_boundary" />
    <value opcode="163" name="unused_shield_door_small" />
    <value opcode="164" name="unused_shield_door_medium" />
    <value opcode="165" name="unused_shield_door_large" />
    <value opcode="166" name="unused_drop_shield_equipment" />
    <value opcode="167" name="machinegun" />
    <value opcode="168" name="machinegun_turret" />
    <value opcode="169" name="plasma_turret_weapon" />
    <value opcode="170" name="mounted_plasma_turret" />
    <value opcode="171" name="unused_shade_turret" />
    <value opcode="172" name="unused_cargo_truck" />
    <value opcode="173" name="unused_cart_electric" />
    <value opcode="174" name="unused_forklift" />
    <value opcode="175" name="unused_military_truck" />
    <value opcode="176" name="unused_oni_van" />
    <value opcode="177" name="warthog_gunner" />
    <value opcode="178" name="warthog_gauss_turret" />
    <value opcode="179" name="warthog_rocket_turret" />
    <value opcode="180" name="scorpion_infantry_gunner" />
    <value opcode="181" name="unused_falcon_grenadier_left" />
    <value opcode="182" name="unused_falcon_grenadier_right" />
    <value opcode="183" name="wraith_infantry_turret" />
    <value opcode="184" name="unused_land_mine" />
    <value opcode="185" name="target_laser" />
    <value opcode="186" name="unused_ff_kill_zone" />
    <value opcode="187" name="unused_ff_plat_1x1_flat" />
    <value opcode="188" name="unused_shade_anti_air" />
    <value opcode="189" name="unused_shade_flak" />
    <value opcode="190" name="shade_plasma" />
    <value opcode="191" name="unused_stasis_field" />
    <value opcode="192" name="forerunner_rifle" />
    <value opcode="193" name="unused_vespid" />
    <value opcode="194" name="spread_gun" />
    <value opcode="195" name="attach_beam" />
    <value opcode="196" name="unused_blast_wave" />
    <value opcode="197" name="reflective_shield" />
    <value opcode="198" name="unused_teleporter" />
    <value opcode="199" name="burst_pistol" />
    <value opcode="200" name="rail_gun" />
    <value opcode="201" name="unused_stasis_rifle" />
    <value opcode="202" name="assault_carbine" />
    <value opcode="203" name="auto_turret" />
    <value opcode="204" name="unused_surfboard" />
    <value opcode="205" name="unused_juggernaut" />
    <value opcode="206" name="xray" />
    <value opcode="207" name="unused_needle_shotgun" />
    <value opcode="208" name="unused_grapple_harpoon" />
    <value opcode="209" name="scaleshot_rifle" />
    <value opcode="210" name="covenant_carbine" />
    <value opcode="211" name="beam_sniper_rifle" />
    <value opcode="212" name="sticky_grenade_launcher" />
    <value opcode="213" name="thruster_pack_equipment" />
    <value opcode="214" name="lmg" />
    <value opcode="215" name="mortar" />
    <value opcode="216" name="stasis_pistol" />
    <value opcode="217" name="disruption_grenade" />
    <value opcode="218" name="unused_active_hacker_equipment" />
    <value opcode="219" name="unused_bishop_beam" />
    <value opcode="220" name="concussion_rifle" />
    <value opcode="221" name="fuel_rod_cannon" />
    <value opcode="222" name="unused_needle_grenade" />
    <value opcode="223" name="unused_blam_beacon" />
    <value opcode="224" name="battle_rifle" />
    <value opcode="225" name="forerunner_smg" />
    <value opcode="226" name="storm_magnum_ctf" />
    <value opcode="227" name="blam_effect" />
    <value opcode="228" name="blam_device" />
    <value opcode="229" name="regen_field_equipment" />
    <value opcode="230" name="unused_dom_interact" />
    <value opcode="231" name="extract_falloff_respawn" />
    <value opcode="232" name="koth_falloff_respawn" />
    <value opcode="233" name="flood_sword" />
    <value opcode="234" name="unused_aa_none" />
    <value opcode="235" name="blam_sound_object_01" />
    <value opcode="236" name="blam_sound_object_02" />
    <value opcode="237" name="blam_sound_object_03" />
    <value opcode="238" name="auto_turret_vehicle" />
    <value opcode="239" name="unused_auto_turret_vehicle_pve" />
    <value opcode="240" name="dom_base_switch" />
    <value opcode="241" name="flood_thruster_pack_equipment" />
    <value opcode="242" name="dom_turret" />
    <value opcode="243" name="odd_falloff_respawn" />
    <value opcode="244" name="extract_anti_respawn" />
    <value opcode="245" name="koth_anti_respawn" />
    <value opcode="246" name="odd_anti_respawn" />
    <value opcode="247" name="bomb_disarm" />
    <value opcode="248" name="blam_emblem" />
    <value opcode="249" name="blam_switch" />
    <value opcode="250" name="blam_sym_switch" />
    <value opcode="251" name="flashing_area" />
    <value opcode="252" name="dominion_screen_flash" />
    <value opcode="253" name="blam_incoming" />
    <value opcode="254" name="koth_incoming" />
    <value opcode="255" name="odd_confetti" />
    <value opcode="256" name="mantis" />
    <value opcode="257" name="carry_bomb" />
    <value opcode="258" name="koth_explosion" />
    <value opcode="259" name="dmr_alt" />
    <value opcode="260" name="magnum_alt" />
    <value opcode="261" name="plasma_pistol_alt" />
    <value opcode="262" name="forerunner_rifle_alt" />
    <value opcode="263" name="covenant_carbine_alt" />
    <value opcode="264" name="forerunner_smg_alt" />
    <value opcode="265" name="stasis_pistol_alt" />
    <value opcode="266" name="battle_rifle_alt" />
    <value opcode="267" name="battle_rifle_alt2" />
    <value opcode="268" name="assault_rifle_alt" />
    <value opcode="269" name="assault_rifle_alt2" />
    <value opcode="270" name="unused_jet_pack_equipment_pve" />
    <value opcode="271" name="unused_forerunner_vision_pve" />
    <value opcode="272" name="unused_auto_turret_pve" />
    <value opcode="273" name="unused_thruster_pack_pve" />
    <value opcode="274" name="unused_active_shield_pve" />
    <value opcode="275" name="unused_sticky_grenade_launcher_pve" />
    <value opcode="276" name="unused_rail_gun_pve" />
    <value opcode="277" name="unused_plasma_pistol_pve" />
    <value opcode="278" name="unused_broadsword" />
    <value opcode="279" name="unused_pelican_cannon" />
    <value opcode="280" name="unused_pelican_side_turret" />
    <value opcode="281" name="unused_pelican_side_turret_mirror" />
    <value opcode="282" name="unused_target_laser_m40" />
    <value opcode="283" name="unused_campaign_mantis" />
    <value opcode="284" name="unused_active_camo_equipment_m20" />
    <value opcode="285" name="banshee_mp" />
    <value opcode="286" name="unused_mammoth_turret" />
    <value opcode="287" name="dom_turret_pad" />
    <value opcode="288" name="unused_auto_turret_vehicle_knight" />
  </enum>
</enums>